db2pq/__init__.py
db2pq/db2pq.py
db2pq-0.1.6.dist-info/licenses/LICENSE
db2pq-0.1.6.dist-info/METADATA
db2pq-0.1.6.dist-info/WHEEL
db2pq-0.1.6.dist-info/top_level.txt
db2pq-0.1.6.dist-info/RECORD
