Metadata-Version: 2.4
Name: db2pq
Version: 0.1.6
Summary: Convert database tables to parquet tables.
Home-page: https://github.com/iangow/db2pq/
Author: Ian Gow
Author-email: iandgow@gmail.com
Classifier: Programming Language :: Python :: 3
Classifier: License :: OSI Approved :: MIT License
Classifier: Operating System :: OS Independent
Requires-Python: >=3
License-File: LICENSE
Requires-Dist: ibis-framework[duckdb,postgres]
Requires-Dist: pyarrow
Requires-Dist: pandas
Requires-Dist: paramiko
Dynamic: author
Dynamic: author-email
Dynamic: classifier
Dynamic: description
Dynamic: description-content-type
Dynamic: home-page
Dynamic: license-file
Dynamic: requires-dist
Dynamic: requires-python
Dynamic: summary
